LICENSE
MANIFEST.in
README
requirements.txt
setup.cfg
setup.py
doc/_build/html/.buildinfo
doc/_build/html/generator.html
doc/_build/html/genindex.html
doc/_build/html/index.html
doc/_build/html/modules.html
doc/_build/html/objects.inv
doc/_build/html/primepackage.html
doc/_build/html/py-modindex.html
doc/_build/html/search.html
doc/_build/html/searchindex.js
doc/_build/html/_sources/generator.rst.txt
doc/_build/html/_sources/index.rst.txt
doc/_build/html/_sources/modules.rst.txt
doc/_build/html/_sources/primepackage.rst.txt
doc/_build/html/_static/basic.css
doc/_build/html/_static/classic.css
doc/_build/html/_static/doctools.js
doc/_build/html/_static/documentation_options.js
doc/_build/html/_static/file.png
doc/_build/html/_static/jquery-3.4.1.js
doc/_build/html/_static/jquery.js
doc/_build/html/_static/language_data.js
doc/_build/html/_static/minus.png
doc/_build/html/_static/plus.png
doc/_build/html/_static/pygments.css
doc/_build/html/_static/searchtools.js
doc/_build/html/_static/sidebar.js
doc/_build/html/_static/underscore-1.3.1.js
doc/_build/html/_static/underscore.js
src/generator
src/primepackage/__init__.py
src/primepackage/primeio.py
src/primepackage/primemodule.py
src/vsucsprime2.egg-info/PKG-INFO
src/vsucsprime2.egg-info/SOURCES.txt
src/vsucsprime2.egg-info/dependency_links.txt
src/vsucsprime2.egg-info/requires.txt
src/vsucsprime2.egg-info/top_level.txt